{"entries":[{"by":"","kost":"560","land":"Øvrige områder","makssatser natt":"1290","verdensdel":"Afrika"},{"by":"","kost":"720","land":"Algerie","makssatser natt":"1750","verdensdel":"Afrika"},{"by":"","kost":"1000","land":"Angola","makssatser natt":"2850","verdensdel":"Afrika"},{"by":"","kost":"440","land":"Benin","makssatser natt":"1100","verdensdel":"Afrika"},{"by":"","kost":"400","land":"Botswana","makssatser natt":"1250","verdensdel":"Afrika"},{"by":"","kost":"300","land":"Burundi","makssatser natt":"900","verdensdel":"Afrika"},{"by":"","kost":"480","land":"Egypt","makssatser natt":"1750","verdensdel":"Afrika"},{"by":"","kost":"960","land":"Elfenbenskysten","makssatser natt":"1900","verdensdel":"Afrika"},{"by":"","kost":"500","land":"Etiopia","makssatser natt":"2200","verdensdel":"Afrika"},{"by":"","kost":"760","land":"Gabon","makssatser natt":"1770","verdensdel":"Afrika"},{"by":"","kost":"300","land":"Gambia","makssatser natt":"1000","verdensdel":"Afrika"},{"by":"","kost":"520","land":"Ghana","makssatser natt":"1880","verdensdel":"Afrika"},{"by":"","kost":"440","land":"Guinea","makssatser natt":"1150","verdensdel":"Afrika"},{"by":"","kost":"490","land":"Kamerun","makssatser natt":"1500","verdensdel":"Afrika"},{"by":"","kost":"580","land":"Kenya","makssatser natt":"2100","verdensdel":"Afrika"},{"by":"","kost":"300","land":"Lesotho","makssatser natt":"1350","verdensdel":"Afrika"},{"by":"","kost":"450","land":"Liberia","makssatser natt":"1160","verdensdel":"Afrika"},{"by":"","kost":"420","land":"Libya","makssatser natt":"3500","verdensdel":"Afrika"},{"by":"","kost":"350","land":"Madagaskar","makssatser natt":"1300","verdensdel":"Afrika"},{"by":"","kost":"740","land":"Malawi","makssatser natt":"1000","verdensdel":"Afrika"},{"by":"","kost":"470","land":"Mali","makssatser natt":"1200","verdensdel":"Afrika"},{"by":"","kost":"700","land":"Marokko","makssatser natt":"2100","verdensdel":"Afrika"},{"by":"","kost":"510","land":"Mauritius","makssatser natt":"1500","verdensdel":"Afrika"},{"by":"","kost":"420","land":"Mozambique","makssatser natt":"1650","verdensdel":"Afrika"},{"by":"","kost":"500","land":"Namibia","makssatser natt":"2100","verdensdel":"Afrika"},{"by":"","kost":"700","land":"Nigeria","makssatser natt":"2500","verdensdel":"Afrika"},{"by":"","kost":"680","land":"Senegal","makssatser natt":"1900","verdensdel":"Afrika"},{"by":"","kost":"600","land":"Seychellene","makssatser natt":"1200","verdensdel":"Afrika"},{"by":"","kost":"400","land":"Sudan Pund SDP","makssatser natt":"1700","verdensdel":"Afrika"},{"by":"","kost":"300","land":"Swasiland","makssatser natt":"1700","verdensdel":"Afrika"},{"by":"","kost":"500","land":"Sør-Afrika","makssatser natt":"2400","verdensdel":"Afrika"},{"by":"Cape Town","kost":"520","land":"Sør-Afrika","makssatser natt":"3300","verdensdel":"Afrika"},{"by":"Johannesburg","kost":"620","land":"Sør-Afrika","makssatser natt":"2400","verdensdel":"Afrika"},{"by":"","kost":"340","land":"Tanzania","makssatser natt":"2000","verdensdel":"Afrika"},{"by":"","kost":"430","land":"Togo","makssatser natt":"1000","verdensdel":"Afrika"},{"by":"","kost":"650","land":"Tunisia","makssatser natt":"2100","verdensdel":"Afrika"},{"by":"","kost":"550","land":"Uganda","makssatser natt":"1900","verdensdel":"Afrika"},{"by":"","kost":"500","land":"Zambia","makssatser natt":"2100","verdensdel":"Afrika"},{"by":"","kost":"380","land":"Zimbabwe","makssatser natt":"1500","verdensdel":"Afrika"},{"by":"","kost":"600","land":"Øvrige områder","makssatser natt":"1650","verdensdel":"Amerika"},{"by":"","kost":"850","land":"Antigua \u0026 Barbuda","makssatser natt":"1900","verdensdel":"Amerika"},{"by":"","kost":"840","land":"Argentina","makssatser natt":"3200","verdensdel":"Amerika"},{"by":"","kost":"740","land":"Bahamas","makssatser natt":"2500","verdensdel":"Amerika"},{"by":"","kost":"720","land":"Barbados","makssatser natt":"1600","verdensdel":"Amerika"},{"by":"","kost":"600","land":"Bermuda (Br)","makssatser natt":"2800","verdensdel":"Amerika"},{"by":"","kost":"250","land":"Bolivia","makssatser natt":"700","verdensdel":"Amerika"},{"by":"","kost":"700","land":"Brasil","makssatser natt":"2000","verdensdel":"Amerika"},{"by":"Rio","kost":"1000","land":"Brasil","makssatser natt":"3000","verdensdel":"Amerika"},{"by":"","kost":"790","land":"Canada","makssatser natt":"2500","verdensdel":"Amerika"},{"by":"","kost":"780","land":"Chile","makssatser natt":"1600","verdensdel":"Amerika"},{"by":"","kost":"600","land":"Colombia","makssatser natt":"2200","verdensdel":"Amerika"},{"by":"","kost":"550","land":"Costa Rica","makssatser natt":"1000","verdensdel":"Amerika"},{"by":"","kost":"500","land":"Cuba","makssatser natt":"1000","verdensdel":"Amerika"},{"by":"","kost":"450","land":"Den dominikanske rep.","makssatser natt":"1200","verdensdel":"Amerika"},{"by":"","kost":"450","land":"Dominica","makssatser natt":"1050","verdensdel":"Amerika"},{"by":"","kost":"450","land":"Equador","makssatser natt":"1200","verdensdel":"Amerika"},{"by":"","kost":"600","land":"Grenada","makssatser natt":"2300","verdensdel":"Amerika"},{"by":"","kost":"550","land":"Guatemala","makssatser natt":"1200","verdensdel":"Amerika"},{"by":"","kost":"250","land":"Guyana","makssatser natt":"1100","verdensdel":"Amerika"},{"by":"","kost":"500","land":"Haiti","makssatser natt":"1000","verdensdel":"Amerika"},{"by":"","kost":"450","land":"Jamaica","makssatser natt":"1500","verdensdel":"Amerika"},{"by":"","kost":"650","land":"Mexico","makssatser natt":"1600","verdensdel":"Amerika"},{"by":"","kost":"460","land":"Nederlandske Antiller","makssatser natt":"1200","verdensdel":"Amerika"},{"by":"","kost":"420","land":"Nicaragua","makssatser natt":"1100","verdensdel":"Amerika"},{"by":"","kost":"350","land":"Panama","makssatser natt":"1100","verdensdel":"Amerika"},{"by":"","kost":"250","land":"Paraguay","makssatser natt":"1000","verdensdel":"Amerika"},{"by":"","kost":"600","land":"Peru","makssatser natt":"1600","verdensdel":"Amerika"},{"by":"","kost":"410","land":"Puerto Rico","makssatser natt":"1500","verdensdel":"Amerika"},{"by":"","kost":"810","land":"St Kitts \u0026 Nevis","makssatser natt":"2000","verdensdel":"Amerika"},{"by":"","kost":"750","land":"St Lucia","makssatser natt":"1700","verdensdel":"Amerika"},{"by":"","kost":"770","land":"St Vincent","makssatser natt":"1700","verdensdel":"Amerika"},{"by":"","kost":"350","land":"Surinam","makssatser natt":"1100","verdensdel":"Amerika"},{"by":"","kost":"740","land":"Trinidad \u0026 Tobago","makssatser natt":"2000","verdensdel":"Amerika"},{"by":"","kost":"520","land":"Uruguay","makssatser natt":"1300","verdensdel":"Amerika"},{"by":"","kost":"730","land":"USA","makssatser natt":"2000","verdensdel":"Amerika"},{"by":"New York by","kost":"950","land":"USA","makssatser natt":"3500","verdensdel":"Amerika"},{"by":"Washington D.C.","kost":"1350","land":"USA","makssatser natt":"3550","verdensdel":"Amerika"},{"by":"","kost":"1000","land":"Venezuela","makssatser natt":"2000","verdensdel":"Amerika"},{"by":"","kost":"680","land":"Øvrige områder","makssatser natt":"1460","verdensdel":"Asia"},{"by":"","kost":"600","land":"Afganistan","makssatser natt":"2100","verdensdel":"Asia"},{"by":"","kost":"500","land":"Armenia","makssatser natt":"1600","verdensdel":"Asia"},{"by":"","kost":"700","land":"Azerbaijan","makssatser natt":"2400","verdensdel":"Asia"},{"by":"","kost":"950","land":"Bahrain","makssatser natt":"2300","verdensdel":"Asia"},{"by":"","kost":"400","land":"Bangladesh","makssatser natt":"1500","verdensdel":"Asia"},{"by":"","kost":"350","land":"Brunei","makssatser natt":"1000","verdensdel":"Asia"},{"by":"","kost":"950","land":"Burma (Myanmar)","makssatser natt":"1700","verdensdel":"Asia"},{"by":"","kost":"590","land":"Fillipinene","makssatser natt":"1900","verdensdel":"Asia"},{"by":"","kost":"700","land":"Forente arabiske emirater","makssatser natt":"1500","verdensdel":"Asia"},{"by":"","kost":"500","land":"Georgia","makssatser natt":"2300","verdensdel":"Asia"},{"by":"","kost":"500","land":"India","makssatser natt":"1900","verdensdel":"Asia"},{"by":"","kost":"760","land":"Indonesia","makssatser natt":"1650","verdensdel":"Asia"},{"by":"","kost":"600","land":"Iran","makssatser natt":"1350","verdensdel":"Asia"},{"by":"","kost":"890","land":"Israel","makssatser natt":"2500","verdensdel":"Asia"},{"by":"","kost":"640","land":"De palestinske områder","makssatser natt":"1200","verdensdel":"Asia"},{"by":"","kost":"900","land":"Japan","makssatser natt":"2350","verdensdel":"Asia"},{"by":"Osaka","kost":"1140","land":"Japan","makssatser natt":"2350","verdensdel":"Asia"},{"by":"Tokyo","kost":"1350","land":"Japan","makssatser natt":"2650","verdensdel":"Asia"},{"by":"","kost":"850","land":"Jordan","makssatser natt":"2200","verdensdel":"Asia"},{"by":"","kost":"850","land":"Kambodia","makssatser natt":"1700","verdensdel":"Asia"},{"by":"","kost":"800","land":"Kazakhstan","makssatser natt":"3000","verdensdel":"Asia"}],"page":1,"pages":2,"posts":192}